backendpy/__init__.py
backendpy/app.py
backendpy/asgi.py
backendpy/config.py
backendpy/db.py
backendpy/error.py
backendpy/exception.py
backendpy/hook.py
backendpy/initializer.py
backendpy/logging.py
backendpy/request.py
backendpy/response.py
backendpy/router.py
backendpy/templating.py
backendpy/unittest.py
backendpy/cli/__init__.py
backendpy/cli/admin.py
backendpy/data_handler/__init__.py
backendpy/data_handler/data.py
backendpy/data_handler/fields.py
backendpy/data_handler/filters.py
backendpy/data_handler/validators.py
backendpy/middleware/__init__.py
backendpy/middleware/middleware.py
backendpy/middleware/defaults/__init__.py
backendpy/middleware/defaults/cors.py
backendpy/utils/__init__.py
backendpy/utils/bytes.py
backendpy/utils/file.py
backendpy/utils/http.py
backendpy/utils/json.py
backendpy-0.2.8a1.dist-info/LICENSE
backendpy-0.2.8a1.dist-info/METADATA
backendpy-0.2.8a1.dist-info/WHEEL
backendpy-0.2.8a1.dist-info/entry_points.txt
backendpy-0.2.8a1.dist-info/top_level.txt
backendpy-0.2.8a1.dist-info/RECORD
