Metadata-Version: 2.1
Name: backendpy
Version: 0.2.8a1
Summary: Async (ASGI) Python web framework
Home-page: https://github.com/savangco/backendpy
Author: Savang Co.
Author-email: backendpy@savang.com
License: BSD 3-Clause License
Project-URL: Bug Tracker, https://github.com/savangco/backendpy/issues
Project-URL: Documentation, https://backendpy.readthedocs.io
Project-URL: Source Code, https://github.com/savangco/backendpy
Keywords: Backendpy,Web,Framework,Python,Async,ASGI
Classifier: Development Status :: 3 - Alpha
Classifier: Environment :: Web Environment
Classifier: Intended Audience :: Developers
Classifier: License :: OSI Approved :: BSD License
Classifier: Programming Language :: Python :: 3
Classifier: Programming Language :: Python :: 3.8
Classifier: Programming Language :: Python :: 3.9
Classifier: Programming Language :: Python :: 3.10
Classifier: Programming Language :: Python :: 3.11
Classifier: Programming Language :: Python :: 3.12
Classifier: Topic :: Internet :: WWW/HTTP
Classifier: Topic :: Internet :: WWW/HTTP :: Dynamic Content
Classifier: Topic :: Software Development
Classifier: Topic :: Software Development :: Libraries :: Application Frameworks
Classifier: Topic :: Software Development :: Libraries :: Python Modules
Requires-Python: >=3.8
License-File: LICENSE
Requires-Dist: aiofiles >=0.8.0
Provides-Extra: full
Requires-Dist: ujson >=5.1.0 ; extra == 'full'
Requires-Dist: asyncpg >=0.25.0 ; extra == 'full'
Requires-Dist: SQLAlchemy >=1.4.31 ; extra == 'full'
Requires-Dist: jinja2 >=3.0.3 ; extra == 'full'
Requires-Dist: Pillow >=9.0.0 ; extra == 'full'
